README.rst
setup.py
gplayproxy/__init__.py
gplayproxy/views.py
gplayproxy.egg-info/PKG-INFO
gplayproxy.egg-info/SOURCES.txt
gplayproxy.egg-info/dependency_links.txt
gplayproxy.egg-info/entry_points.txt
gplayproxy.egg-info/not-zip-safe
gplayproxy.egg-info/requires.txt
gplayproxy.egg-info/top_level.txt